gugu/__init__.py
gugu/base.py
gugu/billboard.py
gugu/classify.py
gugu/config.py
gugu/lowriskintarb.py
gugu/macro.py
gugu/marketdata.py
gugu/reference.py
gugu/stockdata.py
gugu/stockinfo.py
gugu/utility.py
gugu-0.1.4.dist-info/LICENSE
gugu-0.1.4.dist-info/METADATA
gugu-0.1.4.dist-info/WHEEL
gugu-0.1.4.dist-info/top_level.txt
gugu-0.1.4.dist-info/RECORD
