Metadata-Version: 2.1
Name: gugu
Version: 0.1.4
Summary: an api for getting financial data
Home-page: http://www.infodata.cc
Author: TabQ
Author-email: 16621596@qq.com
License: Apache License, Version 2.0
Keywords: Financial Data Crawler
Platform: UNKNOWN
Classifier: Development Status :: 4 - Beta
Classifier: Programming Language :: Python :: 2.6
Classifier: Programming Language :: Python :: 2.7
Classifier: Programming Language :: Python :: 3.2
Classifier: Programming Language :: Python :: 3.3
Classifier: Programming Language :: Python :: 3.4
Classifier: Programming Language :: Python :: 3.5
Requires-Dist: pandas
Requires-Dist: requests
Requires-Dist: lxml
Requires-Dist: simplejson
Requires-Dist: xlrd
